earningspy/__init__.py
earningspy/calendars/__init__.py
earningspy/calendars/earnings.py
earningspy/calendars/utils.py
earningspy/common/__init__.py
earningspy/common/constants.py
earningspy/generators/__init__.py
earningspy/generators/finviz/__init__.py
earningspy/generators/finviz/config.py
earningspy/generators/finviz/constants.py
earningspy/generators/finviz/data.py
earningspy/generators/finviz/main_func.py
earningspy/generators/finviz/portfolio.py
earningspy/generators/finviz/screener.py
earningspy/generators/finviz/utils.py
earningspy/generators/finviz/helper_functions/__init__.py
earningspy/generators/finviz/helper_functions/display_functions.py
earningspy/generators/finviz/helper_functions/error_handling.py
earningspy/generators/finviz/helper_functions/request_functions.py
earningspy/generators/finviz/helper_functions/save_data.py
earningspy/generators/finviz/helper_functions/scraper_functions.py
earningspy/generators/yahoo/__init__.py
earningspy/generators/yahoo/async_timeseries.py
earningspy/generators/yahoo/time_series.py
earningspy/inspectors/__init__.py
earningspy/inspectors/mixins.py
earningspy/inspectors/pead.py
earningspy-0.1.21.dist-info/licenses/LICENSE
tests/calendars/test_calendars.py
tests/generators/test_finviz.py
tests/generators/test_yahoo.py
tests/inspectors/test_pead.py
tests/utils/__init__.py
tests/utils/fixtures.py
earningspy-0.1.21.dist-info/METADATA
earningspy-0.1.21.dist-info/WHEEL
earningspy-0.1.21.dist-info/top_level.txt
earningspy-0.1.21.dist-info/RECORD
