Metadata-Version: 2.4
Name: earningspy
Version: 0.1.21
Summary: Python toolkit for PEAD research and earnings calendar analysis.
Author-email: Alberto Rincones <alberto.rincones@code4road.com>
License: MIT
Project-URL: Homepage, https://github.com/c4road/earningspy
Keywords: earnings,finance,AI,scraper,PEAD,quant
Classifier: Development Status :: 4 - Beta
Classifier: Intended Audience :: Information Technology
Classifier: License :: OSI Approved :: MIT License
Classifier: Topic :: Scientific/Engineering :: Information Analysis
Classifier: Programming Language :: Python :: 3.9
Classifier: Programming Language :: Python :: 3.10
Classifier: Programming Language :: Python :: 3.11
Requires-Python: <3.12,>=3.9
License-File: LICENSE
Requires-Dist: aiohappyeyeballs==2.6.1
Requires-Dist: aiohttp==3.12.15
Requires-Dist: aiosignal==1.4.0
Requires-Dist: async-timeout==5.0.1
Requires-Dist: attrs==25.3.0
Requires-Dist: beautifulsoup4==4.13.4
Requires-Dist: certifi==2025.7.14
Requires-Dist: charset-normalizer==3.4.2
Requires-Dist: contourpy==1.3.0; python_version >= "3.9" and python_version < "3.10"
Requires-Dist: cssselect==1.3.0
Requires-Dist: frozenlist==1.7.0
Requires-Dist: idna==3.10
Requires-Dist: kiwisolver==1.4.7; python_version < "3.10"
Requires-Dist: lxml==6.0.0
Requires-Dist: multidict==6.6.3
Requires-Dist: numpy==2.0.2; python_version == "3.9"
Requires-Dist: pandas==2.3.1
Requires-Dist: propcache==0.3.2
Requires-Dist: python-dateutil==2.9.0.post0
Requires-Dist: pytz==2025.2
Requires-Dist: requests==2.32.4
Requires-Dist: six==1.17.0
Requires-Dist: soupsieve==2.7
Requires-Dist: tenacity==9.1.2
Requires-Dist: tqdm==4.67.1
Requires-Dist: typing-extensions==4.14.1
Requires-Dist: tzdata==2025.2
Requires-Dist: urllib3==2.5.0
Requires-Dist: user-agent==0.1.10
Requires-Dist: yarl==1.20.1
Dynamic: license-file
